edwh_uuid7/__about__.py
edwh_uuid7/__init__.py
edwh_uuid7/core.py
edwh_uuid7-0.2.3.dist-info/METADATA
edwh_uuid7-0.2.3.dist-info/WHEEL
edwh_uuid7-0.2.3.dist-info/entry_points.txt
edwh_uuid7-0.2.3.dist-info/RECORD
