Metadata-Version: 2.4
Name: edwh-uuid7
Version: 0.2.3
Summary: pg_uuidv7-compatible UUID version 7 generation
Author-email: Robin van der Noord <robinvandernoord@gmail.com>
Requires-Python: >=3.10
Requires-Dist: python-dateutil
Provides-Extra: dev
Requires-Dist: edwh; extra == 'dev'
Requires-Dist: hatch; extra == 'dev'
Requires-Dist: pytest; extra == 'dev'
Requires-Dist: pytest-cov; extra == 'dev'
